{
  "source": "part_0014_16032bytes.bin",
  "size_bytes": 16032,
  "alignment": 1,
  "byte_histogram": {
    "0x00": 5868,
    "0x01": 369,
    "0x02": 97,
    "0x03": 241,
    "0x04": 119,
    "0x05": 18,
    "0x06": 128,
    "0x07": 174,
    "0x08": 219,
    "0x09": 20,
    "0x0a": 43,
    "0x0b": 4,
    "0x0c": 99,
    "0x0d": 22,
    "0x0e": 79,
    "0x0f": 175,
    "0x10": 119,
    "0x11": 34,
    "0x12": 1,
    "0x13": 25,
    "0x14": 22,
    "0x15": 49,
    "0x16": 1,
    "0x17": 10,
    "0x18": 196,
    "0x19": 29,
    "0x1a": 7,
    "0x1b": 13,
    "0x1c": 59,
    "0x1d": 20,
    "0x1e": 34,
    "0x1f": 119,
    "0x20": 125,
    "0x21": 10,
    "0x22": 6,
    "0x23": 23,
    "0x24": 6,
    "0x25": 11,
    "0x26": 11,
    "0x27": 7,
    "0x28": 15,
    "0x29": 15,
    "0x2a": 7,
    "0x2b": 16,
    "0x2c": 8,
    "0x2f": 5,
    "0x30": 89,
    "0x31": 8,
    "0x32": 3,
    "0x33": 11,
    "0x34": 4,
    "0x35": 1,
    "0x36": 1,
    "0x37": 5,
    "0x38": 46,
    "0x39": 6,
    "0x3a": 1,
    "0x3b": 6,
    "0x3c": 60,
    "0x3d": 14,
    "0x3e": 20,
    "0x3f": 118,
    "0x40": 114,
    "0x41": 14,
    "0x42": 14,
    "0x43": 33,
    "0x44": 9,
    "0x45": 4,
    "0x46": 5,
    "0x47": 1,
    "0x48": 1,
    "0x49": 3,
    "0x4a": 10,
    "0x4b": 1,
    "0x4c": 3,
    "0x4e": 9,
    "0x4f": 3,
    "0x50": 34,
    "0x51": 10,
    "0x52": 3,
    "0x53": 4,
    "0x54": 10,
    "0x55": 187,
    "0x56": 2,
    "0x57": 30,
    "0x58": 1,
    "0x5a": 40,
    "0x5b": 4,
    "0x5d": 11,
    "0x5e": 5,
    "0x5f": 10,
    "0x60": 123,
    "0x61": 12,
    "0x63": 13,
    "0x64": 2,
    "0x65": 5,
    "0x66": 39,
    "0x67": 1,
    "0x68": 2,
    "0x69": 6,
    "0x6a": 3,
    "0x6b": 10,
    "0x6c": 2,
    "0x6e": 2,
    "0x6f": 5,
    "0x70": 93,
    "0x71": 13,
    "0x72": 1,
    "0x73": 11,
    "0x74": 3,
    "0x75": 16,
    "0x76": 1,
    "0x77": 16,
    "0x78": 30,
    "0x79": 3,
    "0x7a": 6,
    "0x7b": 13,
    "0x7c": 13,
    "0x7d": 17,
    "0x7e": 34,
    "0x7f": 200,
    "0x80": 436,
    "0x81": 37,
    "0x82": 14,
    "0x83": 14,
    "0x84": 14,
    "0x85": 3,
    "0x86": 13,
    "0x87": 30,
    "0x88": 36,
    "0x89": 6,
    "0x8a": 15,
    "0x8b": 4,
    "0x8c": 7,
    "0x8d": 7,
    "0x8e": 15,
    "0x8f": 57,
    "0x90": 21,
    "0x91": 2,
    "0x92": 2,
    "0x93": 4,
    "0x94": 15,
    "0x95": 2,
    "0x96": 8,
    "0x97": 1,
    "0x98": 39,
    "0x99": 16,
    "0x9c": 9,
    "0x9d": 29,
    "0x9e": 3,
    "0x9f": 14,
    "0xa0": 24,
    "0xa1": 5,
    "0xa2": 5,
    "0xa3": 17,
    "0xa4": 12,
    "0xa5": 3,
    "0xa6": 6,
    "0xa7": 3,
    "0xa8": 37,
    "0xa9": 6,
    "0xaa": 163,
    "0xab": 5,
    "0xac": 2,
    "0xad": 1,
    "0xae": 9,
    "0xaf": 25,
    "0xb0": 22,
    "0xb1": 7,
    "0xb3": 4,
    "0xb4": 1,
    "0xb5": 1,
    "0xb7": 5,
    "0xb8": 14,
    "0xb9": 1,
    "0xba": 10,
    "0xbb": 4,
    "0xbc": 15,
    "0xbe": 17,
    "0xbf": 64,
    "0xc0": 263,
    "0xc1": 16,
    "0xc2": 30,
    "0xc3": 41,
    "0xc4": 17,
    "0xc5": 15,
    "0xc6": 42,
    "0xc7": 22,
    "0xc8": 18,
    "0xc9": 1,
    "0xca": 4,
    "0xcb": 22,
    "0xcc": 14,
    "0xcd": 5,
    "0xce": 10,
    "0xcf": 69,
    "0xd0": 9,
    "0xd1": 2,
    "0xd2": 4,
    "0xd3": 5,
    "0xd4": 15,
    "0xd5": 10,
    "0xd6": 11,
    "0xd7": 8,
    "0xd8": 12,
    "0xdb": 15,
    "0xdc": 4,
    "0xdd": 2,
    "0xde": 16,
    "0xdf": 66,
    "0xe0": 178,
    "0xe1": 25,
    "0xe2": 2,
    "0xe3": 24,
    "0xe4": 1,
    "0xe5": 4,
    "0xe6": 2,
    "0xe7": 28,
    "0xe8": 10,
    "0xe9": 6,
    "0xea": 31,
    "0xeb": 9,
    "0xec": 9,
    "0xed": 3,
    "0xee": 5,
    "0xef": 24,
    "0xf0": 170,
    "0xf1": 65,
    "0xf2": 4,
    "0xf3": 52,
    "0xf4": 9,
    "0xf5": 23,
    "0xf6": 6,
    "0xf7": 30,
    "0xf8": 126,
    "0xf9": 20,
    "0xfa": 22,
    "0xfb": 49,
    "0xfc": 140,
    "0xfd": 44,
    "0xfe": 267,
    "0xff": 2174
  },
  "pct_zero": 36.6,
  "pct_ff": 13.6,
  "stride_candidates": [
    {
      "records": 4008,
      "stride": 4
    },
    {
      "records": 2004,
      "stride": 8
    },
    {
      "records": 1336,
      "stride": 12
    },
    {
      "records": 1002,
      "stride": 16
    },
    {
      "records": 668,
      "stride": 24
    }
  ],
  "first_64_hex": "ffffffffffffffffffffffffffffffffffffffffffffffffffffffffffffffffffffffffffffffffffffffffffffffffffffffffffffffffffffffffffffffff",
  "structured_attempts": {
    "4008x4": {
      "first_records": [
        [
          255,
          255,
          255,
          255
        ],
        [
          255,
          255,
          255,
          255
        ],
        [
          255,
          255,
          255,
          255
        ],
        [
          255,
          255,
          255,
          255
        ],
        [
          255,
          255,
          255,
          255
        ]
      ]
    },
    "2004x8": {
      "first_records": [
        [
          255,
          255,
          255,
          255,
          255,
          255,
          255,
          255
        ],
        [
          255,
          255,
          255,
          255,
          255,
          255,
          255,
          255
        ],
        [
          255,
          255,
          255,
          255,
          255,
          255,
          255,
          255
        ],
        [
          255,
          255,
          255,
          255,
          255,
          255,
          255,
          255
        ],
        [
          255,
          255,
          255,
          255,
          255,
          255,
          255,
          255
        ]
      ]
    },
    "1336x12": {
      "first_records": [
        [
          255,
          255,
          255,
          255,
          255,
          255,
          255,
          255,
          255,
          255,
          255,
          255
        ],
        [
          255,
          255,
          255,
          255,
          255,
          255,
          255,
          255,
          255,
          255,
          255,
          255
        ],
        [
          255,
          255,
          255,
          255,
          255,
          255,
          255,
          255,
          255,
          255,
          255,
          255
        ],
        [
          255,
          255,
          255,
          255,
          255,
          255,
          255,
          255,
          255,
          255,
          255,
          255
        ],
        [
          255,
          255,
          255,
          255,
          255,
          255,
          255,
          255,
          255,
          255,
          255,
          255
        ]
      ]
    },
    "1002x16": {
      "first_records": [
        [
          255,
          255,
          255,
          255,
          255,
          255,
          255,
          255,
          255,
          255,
          255,
          255,
          255,
          255,
          255,
          255
        ],
        [
          255,
          255,
          255,
          255,
          255,
          255,
          255,
          255,
          255,
          255,
          255,
          255,
          255,
          255,
          255,
          255
        ],
        [
          255,
          255,
          255,
          255,
          255,
          255,
          255,
          255,
          255,
          255,
          255,
          255,
          255,
          255,
          255,
          255
        ],
        [
          255,
          255,
          255,
          255,
          255,
          255,
          255,
          255,
          255,
          255,
          255,
          255,
          255,
          255,
          255,
          255
        ],
        [
          255,
          255,
          255,
          255,
          255,
          255,
          255,
          255,
          255,
          255,
          255,
          255,
          255,
          255,
          255,
          255
        ]
      ]
    }
  }
}